CdBURY/CdBURY.py
CdBURY/__init__.py
CdBURY/classes.py
CdBURY/core.py
cdbury-0.1.0.dist-info/licenses/LICENCE
cdbury-0.1.0.dist-info/METADATA
cdbury-0.1.0.dist-info/WHEEL
cdbury-0.1.0.dist-info/top_level.txt
cdbury-0.1.0.dist-info/RECORD
