Metadata-Version: 2.4
Name: CdBURY
Version: 0.1.0
Summary: A python package to simulate seawater cadmium isotopes
Author-email: Rossidae <ross.whiteford@rhul.ac.uk>
License-Expression: MIT
Project-URL: Homepage, https://github.com/DISTILL-RHUL/CdBURY
Classifier: Programming Language :: Python :: 3
Classifier: Operating System :: OS Independent
Requires-Python: >=3.9
License-File: LICENCE
Requires-Dist: numpy
Requires-Dist: matplotlib
Requires-Dist: pandas
Dynamic: license-file
